phound/__init__.py
phound/client.py
phound/config.py
phound/event_listener.py
phound/events.py
phound/exceptions.py
phound/handlers.py
phound/logging.py
phound/main.py
phound/server.py
phound/bin/uccrobot
phound/chats/__init__.py
phound/chats/text_helpers.py
phound/chats/utils.py
phound-0.1.8.dist-info/LICENSE
phound-0.1.8.dist-info/METADATA
phound-0.1.8.dist-info/WHEEL
phound-0.1.8.dist-info/top_level.txt
phound-0.1.8.dist-info/RECORD
