Metadata-Version: 2.2
Name: phound
Version: 0.1.8
Summary: Phound SDK
Author: Konstantin Seravin
Author-email: kseravin@freeconferencecall.com
License: MIT
Classifier: Development Status :: 3 - Alpha
Classifier: Intended Audience :: Developers
Classifier: License :: OSI Approved :: MIT License
Requires-Python: >=3.8
License-File: LICENSE
Requires-Dist: python-dotenv==1.0.1
Requires-Dist: pillow==10.3.0
Dynamic: author
Dynamic: author-email
Dynamic: classifier
Dynamic: description
Dynamic: description-content-type
Dynamic: license
Dynamic: requires-dist
Dynamic: requires-python
Dynamic: summary
